__init__.py
test_series.py
unseries.py
unseries-0.1.0.dist-info/DESCRIPTION.rst
unseries-0.1.0.dist-info/METADATA
unseries-0.1.0.dist-info/RECORD
unseries-0.1.0.dist-info/WHEEL
unseries-0.1.0.dist-info/metadata.json
unseries-0.1.0.dist-info/top_level.txt
