Metadata-Version: 2.0
Name: unseries
Version: 0.1.0
Summary: Allows to deal with power series which coefficients contain uncertainties
Home-page: https://github.com/kirienko/unseries
Author: Yury Kirienko
Author-email: yury.kirienko@gmail.com
License: GPL-3.0
Platform: Linux
Platform: Unix
Platform: MacOsX
Platform: Windows
Classifier: Development Status :: 3 - Alpha
Classifier: Intended Audience :: Science/Research
Classifier: Topic :: Software Development :: Build Tools
Classifier: License :: OSI Approved :: GNU General Public License v3 (GPLv3)
Classifier: Programming Language :: Python :: 2.7
Requires-Dist: sympy
Requires-Dist: uncertainties (>=3.0.1)
